sentry_auth_google/__init__.py
sentry_auth_google/constants.py
sentry_auth_google/provider.py
sentry_auth_google/utils.py
sentry_auth_google/views.py
sentry_auth_google/templates/sentry_auth_google/configure.html
sentry_auth_google-0.2.0.dist-info/LICENSE
sentry_auth_google-0.2.0.dist-info/METADATA
sentry_auth_google-0.2.0.dist-info/WHEEL
sentry_auth_google-0.2.0.dist-info/entry_points.txt
sentry_auth_google-0.2.0.dist-info/top_level.txt
sentry_auth_google-0.2.0.dist-info/RECORD
